pangloss/__init__.py
pangloss/backend.py
pangloss/config.py
pangloss/pangloss.py
pangloss/util.py
pangloss-0.2.0.dist-info/DESCRIPTION.rst
pangloss-0.2.0.dist-info/LICENSE.txt
pangloss-0.2.0.dist-info/METADATA
pangloss-0.2.0.dist-info/RECORD
pangloss-0.2.0.dist-info/WHEEL
pangloss-0.2.0.dist-info/entry_points.txt
pangloss-0.2.0.dist-info/metadata.json
pangloss-0.2.0.dist-info/top_level.txt
