Metadata-Version: 2.0
Name: pangloss
Version: 0.2.0
Summary: A pandoc filter for interlinear glosses
Home-page: UNKNOWN
Author: UNKNOWN
Author-email: UNKNOWN
License: UNKNOWN
Platform: UNKNOWN
